setup.py
ckanext/__init__.py
ckanext/nationdata/__init__.py
ckanext/nationdata/controller.py
ckanext/nationdata/plugin.py
ckanext_nationdata.egg-info/PKG-INFO
ckanext_nationdata.egg-info/SOURCES.txt
ckanext_nationdata.egg-info/dependency_links.txt
ckanext_nationdata.egg-info/entry_points.txt
ckanext_nationdata.egg-info/namespace_packages.txt
ckanext_nationdata.egg-info/not-zip-safe
ckanext_nationdata.egg-info/top_level.txt