Metadata-Version: 1.0
Name: ckanext-nationdata
Version: 0.1
Summary: Ckan Extension for the Nation Media Group data portal
Home-page: http://www.afrigeo.com
Author: Jude Mwenda
Author-email: judemwenda@gmail.com
License: GPL 2
Platform: UNKNOWN
